fit_better/README.md
fit_better/README_CN.md
fit_better/__init__.py
fit_better/__init__.py.dox
fit_better/core/__init__.py
fit_better/core/experiment.py
fit_better/core/models.py
fit_better/core/partitioning.py
fit_better/core/regression.py
fit_better/data/__init__.py
fit_better/data/csv_manager.py
fit_better/data/file_loader.py
fit_better/data/preprocessing.py
fit_better/data/synthetic.py
fit_better/evaluation/__init__.py
fit_better/evaluation/metrics.py
fit_better/io/__init__.py
fit_better/io/model_io.py
fit_better/io/export/__init__.py
fit_better/io/export/cpp.py
fit_better/io/export/json.py
fit_better/io/export/__pycache__/__init__.cpython-310.pyc
fit_better/io/export/__pycache__/cpp.cpython-310.pyc
fit_better/models/__init__.py
fit_better/models/sklearn.py
fit_better/utils/README.md
fit_better/utils/__init__.py
fit_better/utils/ascii.py
fit_better/utils/logging_utils.py
fit_better/utils/plotting.py
fit_better/utils/statistics.py
tests/.DS_Store
tests/README.md
tests/__init__.py
tests/conftest.py
tests/run_all_tests.sh
tests/test_all.py
tests/verify_failure_handling.py
tests/unittests/README.md
tests/unittests/__init__.py
tests/unittests/conftest.py
tests/unittests/test_auto_delimiter_detection.py
tests/unittests/test_best_partition_and_regressor.py
tests/unittests/test_clustering_algorithms.py
tests/unittests/test_compare_partitions.py
tests/unittests/test_compare_regressors.py
tests/unittests/test_cpp_integration.py
tests/unittests/test_csv_manager.py
tests/unittests/test_csv_operations.py
tests/unittests/test_data_preprocessing.py
tests/unittests/test_file_loader.py
tests/unittests/test_find_best_partition_and_algo.py
tests/unittests/test_fresh_install.py
tests/unittests/test_io_export.py
tests/unittests/test_kmeans_logistic.py
tests/unittests/test_logistic_regression.py
tests/unittests/test_mlp_and_kmeans_plus_plus.py
tests/unittests/test_mlp_and_kmeans_plusplus.py
tests/unittests/test_model_io.py
tests/unittests/test_model_utils.py
fit_better-0.1.5.dist-info/LICENSE
fit_better-0.1.5.dist-info/METADATA
fit_better-0.1.5.dist-info/WHEEL
fit_better-0.1.5.dist-info/top_level.txt
fit_better-0.1.5.dist-info/RECORD
