Metadata-Version: 2.1
Name: fit-better
Version: 0.1.5
Summary: A package for improved regression modeling with partitioning
Home-page: https://github.com/xlindo/fit-better
Author: xlindo
Author-email: hi@xlindo.com
License: Proprietary
Platform: UNKNOWN
Classifier: Programming Language :: Python :: 3
Classifier: License :: Other/Proprietary License
Classifier: Operating System :: OS Independent
Requires-Python: >=3.6
License-File: LICENSE
Requires-Dist: joblib>=1.0.0
Requires-Dist: matplotlib>=3.3.0
Requires-Dist: numpy>=1.19.0
Requires-Dist: scikit-learn>=0.24.0
Provides-Extra: dev
Requires-Dist: black; extra == "dev"
Requires-Dist: pytest>=6.0.0; extra == "dev"
Provides-Extra: docs
Requires-Dist: markdown; extra == "docs"
Requires-Dist: pdoc>=4.0.0; extra == "docs"
Provides-Extra: extra
Requires-Dist: lightgbm; extra == "extra"
Requires-Dist: xgboost; extra == "extra"
